Workbook
Name Slicer_Product_Name: #N/A
Name Slicer_Region: #N/A
Name Slicer_Salesperson: #N/A

Sheet Sales_Data
A1: Order ID | B1: Date | C1: Product Name | D1: Category | E1: Region | F1: Salesperson | G1: Quantity | H1: Unit Price | I1: Revenue | J1: Target | K1: Profit | L1: Target Status
A2: SO-1001 | B2: 46143 | C2: Laptop | D2: Electronics | E2: West | F2: Priya | G2: 3 | H2: 55000 | I2: =G2*H2 -> 165000 | J2: 150000 | K2: =I2-(G2*VLOOKUP(C2,Product_Master!$B$2:$E$6,4,FALSE)) -> 21000 | L2: =IF(I2>=J2,"Target Achieved","Target Not Achieved") -> Target Achieved
A3: SO-1002 | B3: 46145 | C3: Mobile | D3: Electronics | E3: North | F3: Rahul | G3: 8 | H3: 18000 | I3: =G3*H3 -> 144000 | J3: 120000 | K3: =I3-(G3*VLOOKUP(C3,Product_Master!$B$2:$E$6,4,FALSE)) -> 24000 | L3: =IF(I3>=J3,"Target Achieved","Target Not Achieved") -> Target Achieved
A4: SO-1003 | B4: 46147 | C4: Headphones | D4: Accessories | E4: South | F4: Neha | G4: 20 | H4: 2500 | I4: =G4*H4 -> 50000 | J4: 40000 | K4: =I4-(G4*VLOOKUP(C4,Product_Master!$B$2:$E$6,4,FALSE)) -> 14000 | L4: =IF(I4>=J4,"Target Achieved","Target Not Achieved") -> Target Achieved
A5: SO-1004 | B5: 46149 | C5: Printer | D5: Office | E5: East | F5: Aman | G5: 4 | H5: 12000 | I5: =G5*H5 -> 48000 | J5: 60000 | K5: =I5-(G5*VLOOKUP(C5,Product_Master!$B$2:$E$6,4,FALSE)) -> 12000 | L5: =IF(I5>=J5,"Target Achieved","Target Not Achieved") -> Target Not Achieved
A6: SO-1005 | B6: 46151 | C6: Tablet | D6: Electronics | E6: West | F6: Priya | G6: 5 | H6: 24000 | I6: =G6*H6 -> 120000 | J6: 100000 | K6: =I6-(G6*VLOOKUP(C6,Product_Master!$B$2:$E$6,4,FALSE)) -> 20000 | L6: =IF(I6>=J6,"Target Achieved","Target Not Achieved") -> Target Achieved

Sheet Product_Master
A1: Product ID | B1: Product Name | C1: Category | D1: Unit Price | E1: Cost Price
A2: P-01 | B2: Laptop | C2: Electronics | D2: 55000 | E2: 48000
A3: P-02 | B3: Mobile | C3: Electronics | D3: 18000 | E3: 15000
A4: P-03 | B4: Headphones | C4: Accessories | D4: 2500 | E4: 1800
A5: P-04 | B5: Printer | C5: Office | D5: 12000 | E5: 9000
A6: P-05 | B6: Tablet | C6: Electronics | D6: 24000 | E6: 20000

Sheet Formula_Calculations
A1: Metric | B1: Value
A2: Total Revenue | B2: =SUM(Sales_Data!I:I) -> 527000
A3: Total Profit | B3: =SUM(Sales_Data!K:K) -> 91000
A4: Average Sales | B4: =AVERAGE(Sales_Data!I:I) -> 105400
A5: Highest Sales | B5: =MAX(Sales_Data!I:I) -> 165000
A6: Lowest Sales | B6: =MIN(Sales_Data!I:I) -> 48000
A7: Total Orders | B7: =COUNTA(Sales_Data!A:A)-1 -> 5
A8: Target Achieved | B8: =COUNTIF(Sales_Data!L:L,"Target Achieved") -> 4
A9: Target Not Achieved | B9: =COUNTIF(Sales_Data!L:L,"Target Not Achieved") -> 1

Sheet Pivot_Summary
M2: =ISNUMBER(D13) -> FALSE
A3: Row Labels | B3: Sum of Revenue | D3: Row Labels | E3: Sum of Revenue
A4: East | B4: 48000 | D4: Headphones | E4: 50000
A5: North | B5: 144000 | D5: Laptop | E5: 165000
A6: South | B6: 50000 | D6: Mobile | E6: 144000
A7: West | B7: 285000 | D7: Printer | E7: 48000
A8: Grand Total | B8: 527000 | D8: Tablet | E8: 120000
D9: Grand Total | E9: 527000
A12: Row Labels | B12: Sum of Revenue | D12: Row Labels | E12: Sum of Revenue
A13: Aman | B13: 48000 | D13: 2026 | E13: 527000
A14: Neha | B14: 50000 | D14: May | E14: 527000
A15: Priya | B15: 285000 | D15: Grand Total | E15: 527000
A16: Rahul | B16: 144000
A17: Grand Total | B17: 527000
B38: Region | C38: Total Revenue | E38: Product | F38: Total Revenue | H38: Salesperson | I38: Total Revenue
B39: West | C39: 285000 | E39: Laptop | F39: 165000 | H39: Priya | I39: 285000
B40: North | C40: 144000 | E40: Mobile | F40: 144000 | H40: Rahul | I40: 144000
B41: South | C41: 50000 | E41: Headphones | F41: 50000 | H41: Neha | I41: 50000
B42: East | C42: 48000 | E42: Printer | F42: 48000 | H42: Aman | I42: 48000
E43: Tablet | F43: 120000

Sheet Dashboard
A1: Sales Performance Dashboard
B4: Total Sales | F4: Total Profit | J4: Target Achieved % | N4: Top Product
B5: =SUM(Sales_Data!I2:I6) -> 527000 | F5: 91000 | J5: =SUM(Sales_Data!I2:I6)/SUM(Sales_Data!J2:J6) -> 1.1212766 | N5: Laptop
